skale_contracts/__init__.py
skale_contracts/abi.py
skale_contracts/constants.py
skale_contracts/instance.py
skale_contracts/metadata.py
skale_contracts/network.py
skale_contracts/project.py
skale_contracts/project_factory.py
skale_contracts/skale_contracts.py
skale_contracts/projects/__init__.py
skale_contracts/projects/context.py
skale_contracts/projects/ima.py
skale_contracts/projects/skale_allocator.py
skale_contracts/projects/skale_manager.py
skale_contracts-1.0.1.dist-info/METADATA
skale_contracts-1.0.1.dist-info/WHEEL
skale_contracts-1.0.1.dist-info/top_level.txt
skale_contracts-1.0.1.dist-info/RECORD
