Metadata-Version: 2.1
Name: skale-contracts
Version: 1.0.1
Summary: A tool for access to SKALE smart contracts
Home-page: https://github.com/skalenetwork/skale-contracts
Author: Dmytro Stebaiev
Author-email: dmytro@skalelabs.com
Classifier: Programming Language :: Python :: 3
Classifier: License :: OSI Approved :: GNU Affero General Public License v3
Classifier: Operating System :: OS Independent
Requires-Python: >=3.9
Requires-Dist: parver
Requires-Dist: semver
Requires-Dist: web3 <7,>=6
